puro/__init__.py
puro-0.0.1.dist-info/DESCRIPTION.rst
puro-0.0.1.dist-info/METADATA
puro-0.0.1.dist-info/RECORD
puro-0.0.1.dist-info/WHEEL
puro-0.0.1.dist-info/metadata.json
puro-0.0.1.dist-info/top_level.txt
