Metadata-Version: 2.0
Name: puro
Version: 0.0.1
Summary: Highly configurable data streams
Home-page: https://github.com/jvtm/puro
Author: Jyrki Muukkonen
Author-email: jvtm@kruu.org
License: Apache 2.0
Keywords: data streams json
Platform: UNKNOWN
Classifier: Development Status :: 3 - Alpha
Classifier: Intended Audience :: Developers
Classifier: Topic :: Software Development :: Build Tools
Classifier: License :: OSI Approved :: Apache Software License
Classifier: Programming Language :: Python :: 3
Classifier: Programming Language :: Python :: 3.6
Requires-Dist: aiohttp
Requires-Dist: jsonschema
Provides-Extra: test
Requires-Dist: coverage; extra == 'test'
